cert_uefi_parser-1.0.7.dist-info/licenses/LICENSE.md
uefi_parser/__init__.py
uefi_parser/acpi.py
uefi_parser/amd.py
uefi_parser/ami.py
uefi_parser/apple.py
uefi_parser/asn1.py
uefi_parser/auto.py
uefi_parser/base.py
uefi_parser/bgscript.py
uefi_parser/bootguard.py
uefi_parser/cmds.py
uefi_parser/compression.py
uefi_parser/coreboot.py
uefi_parser/devicetree.py
uefi_parser/dxedep.py
uefi_parser/efiguid.py
uefi_parser/exes.py
uefi_parser/finder.py
uefi_parser/fit.py
uefi_parser/flash.py
uefi_parser/fsp.py
uefi_parser/gecko.py
uefi_parser/gui.py
uefi_parser/gui_helper.py
uefi_parser/guiddb.py
uefi_parser/icon.py
uefi_parser/lua.py
uefi_parser/me.py
uefi_parser/mypy.py
uefi_parser/mystery.py
uefi_parser/nvvars.py
uefi_parser/pfs.py
uefi_parser/plf.py
uefi_parser/qhexview.py
uefi_parser/sbom.py
uefi_parser/smbios.py
uefi_parser/test_construct.py
uefi_parser/tpm.py
uefi_parser/uefi.py
uefi_parser/uenum.py
uefi_parser/utils.py
uefi_parser/vendor.py
cert_uefi_parser-1.0.7.dist-info/METADATA
cert_uefi_parser-1.0.7.dist-info/WHEEL
cert_uefi_parser-1.0.7.dist-info/entry_points.txt
cert_uefi_parser-1.0.7.dist-info/top_level.txt
cert_uefi_parser-1.0.7.dist-info/RECORD
