Metadata-Version: 2.4
Name: cert-uefi-parser
Version: 1.0.7
Summary: Various data structures and parsing tools for UEFI firmware.
Author-email: CERT Threat Analysis Team <cert@cert.org>
License: # CERT UEFI Parser License
Project-URL: Homepage, https://github.com/cmu-sei/cert-uefi-parser
Project-URL: Repository, https://github.com/cmu-sei/cert-uefi-parser
Project-URL: Issues, https://github.com/cmu-sei/cert-uefi-parser/issues
Keywords: uefi,firmware,uefi-parser,support-tools,security,bios
Classifier: Development Status :: 4 - Beta
Classifier: Intended Audience :: System Administrators
Classifier: Topic :: Security
Classifier: Programming Language :: Python :: 3
Classifier: License :: Other/Proprietary License
Classifier: Topic :: Security
Classifier: Topic :: System :: Hardware
Requires-Python: >=3.10
License-File: LICENSE.md
Requires-Dist: typing_extensions
Requires-Dist: construct>=2.10.70
Requires-Dist: pefile
Requires-Dist: asn1crypto
Requires-Dist: uswid
Requires-Dist: cert-uefi-support
Provides-Extra: qt
Requires-Dist: PySide6; extra == "qt"
Dynamic: license-file
